setupppy/Logger.py
setupppy/__init__.py
setupppy/main.py
setupppy/utils.py
setupppy-0.2.dist-info/METADATA
setupppy-0.2.dist-info/WHEEL
setupppy-0.2.dist-info/entry_points.txt
setupppy-0.2.dist-info/top_level.txt
setupppy-0.2.dist-info/RECORD
